dipas/__init__.py
dipas/aux.py
dipas/backends.py
dipas/build.py
dipas/cli.py
dipas/compute.py
dipas/elements.py
dipas/external.py
dipas/optimize.py
dipas/plot.py
dipas/utils.py
dipas/madx/__init__.py
dipas/madx/builder.py
dipas/madx/elements.py
dipas/madx/parser.py
dipas/madx/utils.py
dipas/templates/command.css.j2
dipas/templates/command.html.j2
dipas/templates/command.madx.j2
dipas/templates/errors.madx.j2
dipas/templates/script.madx.j2
dipas/templates/sequence.html.j2
dipas/templates/sequence.madx.j2
dipas/templates/track.madx.j2
dipas/templates/icons/collimator.svg
dipas/templates/icons/drift.svg
dipas/templates/icons/generate_css.py
dipas/templates/icons/hkicker.svg
dipas/templates/icons/hmonitor.svg
dipas/templates/icons/instrument.svg
dipas/templates/icons/kicker.svg
dipas/templates/icons/monitor.svg
dipas/templates/icons/quadrupole.svg
dipas/templates/icons/rbend.svg
dipas/templates/icons/sbend.svg
dipas/templates/icons/sextupole.svg
dipas/templates/icons/tkicker.svg
dipas/templates/icons/vkicker.svg
dipas/templates/icons/vmonitor.svg
dipas/test/README.rst
dipas/test/mocks.py
dipas/test/test_aux.py
dipas/test/test_build.py
dipas/test/test_cli.py
dipas/test/test_compute.py
dipas/test/test_elements.py
dipas/test/test_external.py
dipas/test/test_madx.py
dipas/test/test_optimize.py
dipas/test/test_plot.py
dipas/test/test_sequences.py
dipas/test/test_tools.py
dipas/test/test_utils.py
dipas/test/sequences/__init__.py
dipas/test/sequences/cryring.seq
dipas/test/sequences/hades.seq
dipas/test/sequences/load_sequence.py
dipas/test/sequences/sis18.seq
dipas/test/sequences/testfrom.seq
dipas/tools/__init__.py
dipas/tools/madx_to_html.py
dipas/tools/print_beam.py
DiPAS-2.0.dist-info/LICENSE
DiPAS-2.0.dist-info/METADATA
DiPAS-2.0.dist-info/WHEEL
DiPAS-2.0.dist-info/entry_points.txt
DiPAS-2.0.dist-info/top_level.txt
DiPAS-2.0.dist-info/RECORD
