Metadata-Version: 2.1
Name: DiPAS
Version: 2.0
Summary: DiPAS is a framework for differentiable simulations of particle accelerators.
Home-page: https://gitlab.com/Dominik1123/dipas
Author: Dominik Vilsmeier
Author-email: d.vilsmeier@gsi.de
License: GPL-3.0
Project-URL: Documentation, https://dipas.readthedocs.io/en/stable/
Project-URL: Code, https://gitlab.com/Dominik1123/dipas
Project-URL: Issue tracker, https://gitlab.com/Dominik1123/dipas/-/issues
Keywords: simulation,framework,particle tracking,accelerator,optimization,differentiable,particle accelerator
Platform: UNKNOWN
Classifier: Development Status :: 5 - Production/Stable
Classifier: Intended Audience :: Science/Research
Classifier: License :: OSI Approved :: GNU General Public License v3 or later (GPLv3+)
Classifier: Programming Language :: Python :: 3.7
Classifier: Programming Language :: Python :: 3.8
Classifier: Programming Language :: Python :: 3.9
Classifier: Topic :: Scientific/Engineering :: Physics
Requires-Python: >=3.7
Requires-Dist: click (>=7.1)
Requires-Dist: click-inspect (>=0.3.2)
Requires-Dist: jinja2 (>=2.10.1)
Requires-Dist: matchable
Requires-Dist: matplotlib
Requires-Dist: numpy (>=1.21.0)
Requires-Dist: pandas (>=0.25.1)
Requires-Dist: pint (>=0.9)
Requires-Dist: rich
Requires-Dist: scipy (>=1.5.0)
Requires-Dist: torch (>=1.10.0)
Requires-Dist: typing-extensions (>=3.7.4)
